lazynovel/__init__.py
lazynovel/crawler_changdu.py
lazynovel/crawler_mbookcn.py
lazynovel/crawler_reading163.py
lazynovel/open_changdu.py
lazynovel/open_dianzhong.py
lazynovel/open_mbookcn.py
lazynovel/open_reading163.py
lazynovel/open_yangguang.py
lazynovel/open_yiqbook.py
lazynovel/open_yuewen.py
lazynovel/crawler/__init__.py
lazynovel/crawler/changdu.py
lazynovel/crawler/reading163.py
lazynovel/crawler/yuewen.py
lazynovel/open/__init__.py
lazynovel/open/changdu.py
lazynovel/open/qimao.py
lazynovel/open/reading_163.py
lazynovel/open/yuewen.py
lazynovel-0.1.71.dist-info/licenses/LICENSE
test/__init__.py
test/test.py
lazynovel-0.1.71.dist-info/METADATA
lazynovel-0.1.71.dist-info/WHEEL
lazynovel-0.1.71.dist-info/top_level.txt
lazynovel-0.1.71.dist-info/RECORD
