Metadata-Version: 2.4
Name: lazynovel
Version: 0.1.71
Summary: 小说平台接口封包
Home-page: https://gitee.com/ZeroSeeker/lazynovel
Author: ZeroSeeker
Author-email: zeroseeker@foxmail.com
Classifier: Programming Language :: Python :: 3
Classifier: Operating System :: OS Independent
License-File: LICENSE
Requires-Dist: lazysdk>=0.2.0
Dynamic: author
Dynamic: author-email
Dynamic: classifier
Dynamic: description
Dynamic: description-content-type
Dynamic: home-page
Dynamic: license-file
Dynamic: requires-dist
Dynamic: summary
